Metadata-Version: 2.1
Name: dreamlog25-calc-project
Version: 1.0
Summary: простий калькулятор
Author: Oleksii
Author-email: oleksiivoliamyk@gmail.com
